mfc_video_utils/__init__.py
mfc_video_utils-1.0.0.dist-info/DESCRIPTION.rst
mfc_video_utils-1.0.0.dist-info/METADATA
mfc_video_utils-1.0.0.dist-info/RECORD
mfc_video_utils-1.0.0.dist-info/WHEEL
mfc_video_utils-1.0.0.dist-info/metadata.json
mfc_video_utils-1.0.0.dist-info/top_level.txt
