Metadata-Version: 2.0
Name: mfc-video-utils
Version: 1.0.0
Summary: Tools to process videos for the MFC Evaluations
Home-page: UNKNOWN
Author: David Güera, Sriram Baireddy
Author-email: dgueraco@purdue.edu, sbairedd@purdue.edu
License: MIT
Platform: UNKNOWN
